odoo10_addon_project_issue_code-10.0.1.1.0-nspkg.pth
odoo/addons/project_issue_code/README.rst
odoo/addons/project_issue_code/__init__.py
odoo/addons/project_issue_code/__manifest__.py
odoo/addons/project_issue_code/hooks.py
odoo/addons/project_issue_code/data/project_issue_sequence.xml
odoo/addons/project_issue_code/i18n/bg.po
odoo/addons/project_issue_code/i18n/de.po
odoo/addons/project_issue_code/i18n/es.po
odoo/addons/project_issue_code/i18n/fi.po
odoo/addons/project_issue_code/i18n/fr.po
odoo/addons/project_issue_code/i18n/hr.po
odoo/addons/project_issue_code/i18n/it.po
odoo/addons/project_issue_code/i18n/nl.po
odoo/addons/project_issue_code/i18n/nl_NL.po
odoo/addons/project_issue_code/i18n/project_issue_code.pot
odoo/addons/project_issue_code/i18n/pt.po
odoo/addons/project_issue_code/i18n/pt_BR.po
odoo/addons/project_issue_code/i18n/pt_PT.po
odoo/addons/project_issue_code/i18n/sk.po
odoo/addons/project_issue_code/i18n/sl.po
odoo/addons/project_issue_code/i18n/tr.po
odoo/addons/project_issue_code/models/__init__.py
odoo/addons/project_issue_code/models/project_issue.py
odoo/addons/project_issue_code/static/description/icon.png
odoo/addons/project_issue_code/tests/__init__.py
odoo/addons/project_issue_code/tests/test_project_issue_code.py
odoo/addons/project_issue_code/views/project_issue_view.xml
odoo10_addon_project_issue_code-10.0.1.1.0.dist-info/METADATA
odoo10_addon_project_issue_code-10.0.1.1.0.dist-info/WHEEL
odoo10_addon_project_issue_code-10.0.1.1.0.dist-info/namespace_packages.txt
odoo10_addon_project_issue_code-10.0.1.1.0.dist-info/top_level.txt
odoo10_addon_project_issue_code-10.0.1.1.0.dist-info/RECORD
